traquitanas/__init__.py
traquitanas/data/__init__.py
traquitanas/data/convert_to_sql.py
traquitanas/enderecos/__init__.py
traquitanas/enderecos/gerador_endereco.py
traquitanas/files/__init__.py
traquitanas/files/utils.py
traquitanas/net/__init__.py
traquitanas/net/downloads.py
traquitanas/net/ssss.py
traquitanas/numbers/__init__.py
traquitanas/numbers/numbers.py
traquitanas/pessoas/__init__.py
traquitanas/pessoas/personal.py
traquitanas/scrapping/__init__.py
traquitanas/scrapping/adds.py
traquitanas/scrapping/gecko.py
traquitanas/scrapping/paths.py
traquitanas/scrapping/scrapping.py
traquitanas-1.0.59.dist-info/LICENSE
traquitanas-1.0.59.dist-info/METADATA
traquitanas-1.0.59.dist-info/WHEEL
traquitanas-1.0.59.dist-info/top_level.txt
traquitanas-1.0.59.dist-info/RECORD
