Metadata-Version: 2.1
Name: traquitanas
Version: 1.0.59
Summary: Um tanto de coisa!
Home-page: https://github.com/traquitanas/traquitanas
Author: Michel Metran
Author-email: michelmetran@gmail.com
Keywords: python,funções aleatórias
Classifier: Programming Language :: Python :: 3
Classifier: License :: OSI Approved :: MIT License
Classifier: Operating System :: OS Independent
Classifier: Natural Language :: Portuguese
Classifier: Intended Audience :: Developers
Requires-Python: >=3
License-File: LICENSE
Requires-Dist: requests (>=2.25.0)
Requires-Dist: setuptools (>=58.2.0)
Requires-Dist: chardet (>=4.0.0)
Requires-Dist: folium (>=0.12.0)
Requires-Dist: tqdm (>=4.50.0)
Requires-Dist: click (>=8.0.0)
Requires-Dist: selenium (>=4.4.0)
Requires-Dist: pycep-correios
